condynsate/__init__.py
condynsate/exceptions.py
condynsate/__assets__/Cone_1x1_center_origin.stl
condynsate/__assets__/Cone_1x1_lower_origin.stl
condynsate/__assets__/Cube_1x1x1_center_origin.stl
condynsate/__assets__/Cube_1x1x1_lower_origin.stl
condynsate/__assets__/Cylinder_1x1_center_origin.stl
condynsate/__assets__/Cylinder_1x1_lower_origin.stl
condynsate/__assets__/Pyramid_1x1x1_center_origin.stl
condynsate/__assets__/Pyramid_1x1x1_lower_origin.stl
condynsate/__assets__/Sphere_1_center_origin.stl
condynsate/__assets__/Sphere_1_lower_origin.stl
condynsate/__assets__/arrow_ccw.stl
condynsate/__assets__/arrow_lin.stl
condynsate/__assets__/bricks.png
condynsate/__assets__/carpet.png
condynsate/__assets__/cart.urdf
condynsate/__assets__/classroom_wall.png
condynsate/__assets__/concrete.png
condynsate/__assets__/cube.urdf
condynsate/__assets__/door_wall.png
condynsate/__assets__/double_pendulum.urdf
condynsate/__assets__/gyro.urdf
condynsate/__assets__/gyrocore.stl
condynsate/__assets__/gyroouter_1-ODx0.9ID_lower_origin.stl
condynsate/__assets__/gyroring_0.6-ODx0.3-ID_center_origin.stl
condynsate/__assets__/gyroring_0.9-ODx0.6-ID_center_origin.stl
condynsate/__assets__/half_plane_medium.urdf
condynsate/__assets__/missing_tex.png
condynsate/__assets__/pendulum.urdf
condynsate/__assets__/plane.obj
condynsate/__assets__/plane_big.urdf
condynsate/__assets__/plane_medium.urdf
condynsate/__assets__/plane_small.urdf
condynsate/__assets__/white_wall.png
condynsate/__assets__/window_wall.png
condynsate/animator/__init__.py
condynsate/animator/animator.py
condynsate/animator/figure.py
condynsate/animator/subplots.py
condynsate/keyboard/__init__.py
condynsate/keyboard/keyboard.py
condynsate/misc/__init__.py
condynsate/misc/exception_handling.py
condynsate/misc/transforms.py
condynsate/misc/videomaker.py
condynsate/project/__init__.py
condynsate/project/project.py
condynsate/simulator/__init__.py
condynsate/simulator/dataclasses.py
condynsate/simulator/objects.py
condynsate-1.0.5.dist-info/licenses/COPYING
condynsate-1.0.5.dist-info/METADATA
condynsate-1.0.5.dist-info/WHEEL
condynsate-1.0.5.dist-info/top_level.txt
condynsate-1.0.5.dist-info/RECORD
