Metadata-Version: 2.4
Name: condynsate
Version: 1.0.5
Summary: condynsate (control and dynamics simulator) is a tool for teaching dynamics, control, and coding in Python.
Author-email: Grayson Schaer <gschaer2@illinois.edu>
Maintainer-email: Grayson Schaer <gschaer2@illinois.edu>
License-Expression: GPL-3.0-only AND MIT
Project-URL: Homepage, https://condynsate.github.io/condynsate/
Project-URL: Bug Reports, https://github.com/condynsate/condynsate/issues
Project-URL: Source, https://github.com/condynsate/condynsate
Keywords: control and dynamics,visualization,simulation,education,python
Classifier: Programming Language :: Python :: 3
Classifier: Development Status :: 5 - Production/Stable
Classifier: Natural Language :: English
Classifier: Operating System :: Microsoft :: Windows
Classifier: Operating System :: POSIX :: Linux
Classifier: Topic :: Education :: Computer Aided Instruction (CAI)
Classifier: Topic :: Games/Entertainment :: Simulation
Classifier: Topic :: Scientific/Engineering :: Visualization
Requires-Python: >=3.8
License-File: COPYING
Requires-Dist: ipython>=5
Requires-Dist: matplotlib
Requires-Dist: notebook
Requires-Dist: numpy>=1.14.0
Requires-Dist: opencv-python
Requires-Dist: pillow>=7.0.0
Requires-Dist: pybullet
Requires-Dist: pyngrok>=4.1.6
Requires-Dist: pynput
Requires-Dist: pyzmq>=17.0.0
Requires-Dist: tornado>=4.0.0
Requires-Dist: u-msgpack-python>=2.4.1
Provides-Extra: dev
Requires-Dist: spyder; extra == "dev"
Requires-Dist: notebook; extra == "dev"
Requires-Dist: twine; extra == "dev"
Requires-Dist: build; extra == "dev"
Requires-Dist: sphinx; extra == "dev"
Requires-Dist: sphinx-collections; extra == "dev"
Requires-Dist: numpydoc; extra == "dev"
Requires-Dist: autoclasstoc; extra == "dev"
Requires-Dist: sphinx-rtd-theme; extra == "dev"
Requires-Dist: nbsphinx; extra == "dev"
Dynamic: license-file
